sinegy_python/__init__.py
sinegy_python/base.py
sinegy_python/marketplace.py
sinegy_python-0.3.dist-info/LICENSE
sinegy_python-0.3.dist-info/METADATA
sinegy_python-0.3.dist-info/WHEEL
sinegy_python-0.3.dist-info/top_level.txt
sinegy_python-0.3.dist-info/RECORD
