Metadata-Version: 2.1
Name: sinegy-python
Version: 0.3
Summary: Python library for connecting to the Sinegy API.
Home-page: https://github.com/Ipad90/sinegy-python
Author: James Ong Rui Ming
Author-email: jamesong054@gmail.com
License: UNKNOWN
Project-URL: Bug Tracker, https://github.com/Ipad90/sinegy-python/issues
Platform: UNKNOWN
Classifier: Programming Language :: Python :: 3
Classifier: License :: OSI Approved :: MIT License
Classifier: Operating System :: OS Independent
Requires-Python: >=3.6
